emmet/__init__.py
emmet/config.py
emmet/list_utils.py
emmet/output_stream.py
emmet/scanner.py
emmet/scanner_utils.py
emmet/token_scanner.py
emmet/abbreviation/__init__.py
emmet/abbreviation/convert.py
emmet/abbreviation/stringify.py
emmet/abbreviation/parser/__init__.py
emmet/abbreviation/tokenizer/__init__.py
emmet/abbreviation/tokenizer/tokens.py
emmet/abbreviation/tokenizer/utils.py
emmet/action_utils/__init__.py
emmet/action_utils/css.py
emmet/action_utils/html.py
emmet/action_utils/utils.py
emmet/css_abbreviation/__init__.py
emmet/css_abbreviation/parser.py
emmet/css_abbreviation/tokenizer/__init__.py
emmet/css_abbreviation/tokenizer/tokens.py
emmet/css_matcher/__init__.py
emmet/css_matcher/parse.py
emmet/css_matcher/scan.py
emmet/extract_abbreviation/__init__.py
emmet/extract_abbreviation/brackets.py
emmet/extract_abbreviation/is_html.py
emmet/extract_abbreviation/reader.py
emmet/html_matcher/__init__.py
emmet/html_matcher/attributes.py
emmet/html_matcher/scan.py
emmet/html_matcher/utils.py
emmet/markup/__init__.py
emmet/markup/attributes.py
emmet/markup/implicit_tag.py
emmet/markup/snippets.py
emmet/markup/utils.py
emmet/markup/addon/__init__.py
emmet/markup/addon/bem.py
emmet/markup/addon/label.py
emmet/markup/addon/xsl.py
emmet/markup/format/__init__.py
emmet/markup/format/comment.py
emmet/markup/format/html.py
emmet/markup/format/indent_format.py
emmet/markup/format/template.py
emmet/markup/format/utils.py
emmet/markup/format/walk.py
emmet/markup/lorem/__init__.py
emmet/markup/lorem/latin.py
emmet/markup/lorem/russian.py
emmet/markup/lorem/spanish.py
emmet/math_expression/__init__.py
emmet/math_expression/extract.py
emmet/math_expression/parser.py
emmet/snippets/__init__.py
emmet/snippets/css.py
emmet/snippets/html.py
emmet/snippets/pug.py
emmet/snippets/variables.py
emmet/snippets/xsl.py
emmet/stylesheet/__init__.py
emmet/stylesheet/color.py
emmet/stylesheet/format.py
emmet/stylesheet/scope.py
emmet/stylesheet/score.py
emmet/stylesheet/snippets.py
py_emmet-1.3.1.dist-info/LICENSE
py_emmet-1.3.1.dist-info/METADATA
py_emmet-1.3.1.dist-info/WHEEL
py_emmet-1.3.1.dist-info/top_level.txt
py_emmet-1.3.1.dist-info/RECORD
