Metadata-Version: 2.1
Name: py-emmet
Version: 1.3.1
Summary: Emmet is a web-developer’s toolkit for boosting HTML & CSS code writing.
Home-page: https://github.com/emmetio/py-emmet
Author: Sergey Chikuyonok
Author-email: serge.che@gmail.com
Classifier: Programming Language :: Python :: 3
Classifier: License :: OSI Approved :: MIT License
Classifier: Operating System :: OS Independent
Requires-Python: >=3.3
License-File: LICENSE
